neuromeka_hri/__init__.py
neuromeka_hri/get_device_data.py
neuromeka_hri/neuromeka_hri_install.py
neuromeka_hri/teleop_server.py
neuromeka_hri/test.py
neuromeka_hri/apk_file/skill-teaching-phone.apk
neuromeka_hri/common/__init__.py
neuromeka_hri/common/config.py
neuromeka_hri/common/dcp_addr.py
neuromeka_hri/common/global_timer.py
neuromeka_hri/common/jsmin.py
neuromeka_hri/common/limits.py
neuromeka_hri/common/singleton_meta.py
neuromeka_hri/common/utils.py
neuromeka_hri/common/version.py
neuromeka_hri/common/property/Application.py
neuromeka_hri/common/property/Collision.py
neuromeka_hri/common/property/Log.py
neuromeka_hri/common/property/Modbus.py
neuromeka_hri/common/property/Motion.py
neuromeka_hri/common/property/Timer.py
neuromeka_hri/common/property/TrackConveyor.py
neuromeka_hri/common/property/Vision.py
neuromeka_hri/common/property/__init__.py
neuromeka_hri/interfaces/__init__.py
neuromeka_hri/interfaces/config_socket_client.py
neuromeka_hri/interfaces/control_socket_client.py
neuromeka_hri/interfaces/rtde_socket_client.py
neuromeka_hri/interfaces/teleop_external_calibration.py
neuromeka_hri/interfaces/teleop_external_program.py
neuromeka_hri/interfaces/teleop_server_dummy.py
neuromeka_hri/interfaces/teleop_server_vive.py
neuromeka_hri/interfaces/vive/__init__.py
neuromeka_hri/interfaces/vive/triad_openvr.py
neuromeka_hri/managers/__init__.py
neuromeka_hri/managers/config_manager.py
neuromeka_hri/managers/hri_manager.py
neuromeka_hri/managers/log_manager.py
neuromeka_hri/managers/vision_manager.py
neuromeka_hri-0.0.1.dist-info/LICENSE
neuromeka_hri-0.0.1.dist-info/METADATA
neuromeka_hri-0.0.1.dist-info/WHEEL
neuromeka_hri-0.0.1.dist-info/entry_points.txt
neuromeka_hri-0.0.1.dist-info/top_level.txt
neuromeka_hri-0.0.1.dist-info/RECORD
