Metadata-Version: 2.1
Name: neuromeka-hri
Version: 0.0.1
Summary: Neuromeka protocols for HRI system
Home-page: https://github.com/neuromeka-robotics/neuromeka-package
Author: Neuromeka
Author-email: technical-support@neuromeka.com
Classifier: Development Status :: 3 - Alpha
Classifier: Intended Audience :: Developers
Classifier: License :: OSI Approved :: MIT License
Classifier: Operating System :: OS Independent
Classifier: Programming Language :: Python :: 3.7
Classifier: Programming Language :: Python :: 3.8
Classifier: Programming Language :: Python :: 3.9
Classifier: Programming Language :: Python :: 3.10
Classifier: Programming Language :: Python :: 3.11
Requires-Python: >=3.7, <3.12
License-File: LICENSE
Requires-Dist: neuromeka==3.3.2.3
Requires-Dist: scipy
Requires-Dist: openvr
Requires-Dist: dtw
Requires-Dist: dtaidistance
Requires-Dist: matplotlib
